sensospot_parser/__init__.py
sensospot_parser/columns.py
sensospot_parser/csv_parser.py
sensospot_parser/parameters.py
sensospot_parser/xml_parser.py
sensospot_parser-2.0.2.dist-info/entry_points.txt
sensospot_parser-2.0.2.dist-info/LICENSE
sensospot_parser-2.0.2.dist-info/WHEEL
sensospot_parser-2.0.2.dist-info/METADATA
sensospot_parser-2.0.2.dist-info/RECORD
