Metadata-Version: 2.1
Name: sensospot_parser
Version: 2.0.2
Summary: Sensospot Data Parser
Author-email: Holger Frey <frey@imtek.de>
Requires-Python: >=3.9
Classifier: Development Status :: 5 - Production/Stable
Classifier: Intended Audience :: Developers
Classifier: Intended Audience :: Science/Research
Classifier: Programming Language :: Python :: 3.8
Classifier: Programming Language :: Python :: 3.9
Classifier: Programming Language :: Python :: 3.10
Classifier: Programming Language :: Python :: 3 :: Only
Classifier: Topic :: Scientific/Engineering
Classifier: License :: Freely Distributable
Requires-Dist: click
Requires-Dist: defusedxml >=0.6.0
Requires-Dist: pandas >=1.0.0
Requires-Dist: tables >=3.6.1
Requires-Dist: black ; extra == "dev"
Requires-Dist: flit ; extra == "dev"
Requires-Dist: keyring ; extra == "dev"
Requires-Dist: pre-commit ; extra == "dev"
Requires-Dist: ruff ; extra == "dev"
Requires-Dist: mkdocs ; extra == "docs"
Requires-Dist: mkdocstrings[python] ; extra == "docs"
Requires-Dist: pytest >=4.0.0 ; extra == "test"
Requires-Dist: pytest-cov ; extra == "test"
Requires-Dist: pytest-mock ; extra == "test"
Requires-Dist: pytest-randomly >=3.5.0 ; extra == "test"
Requires-Dist: nox ; extra == "test"
Project-URL: Source, https://git.cpi.imtek.uni-freiburg.de/holgi/sensospot_parser.git
Provides-Extra: dev
Provides-Extra: docs
Provides-Extra: test
